README.md
requirements.txt
setup.cfg
setup.py
Aeionss.egg-info/PKG-INFO
Aeionss.egg-info/SOURCES.txt
Aeionss.egg-info/dependency_links.txt
Aeionss.egg-info/requires.txt
Aeionss.egg-info/top_level.txt
aselib/AESEncryption.py