Metadata-Version: 2.1
Name: Aeionss
Version: 0.1
Summary: Homefats Libraries
Home-page: UNKNOWN
Author: Homefacts
Author-email: homefactsinfra@gmail.com
License: UNKNOWN
Keywords: pip,homefacts
Platform: UNKNOWN
